Workbook

Sheet Project Instructions
A1: PR. 1 Fundamental Booster
A2: Topics: - Relative & Absolute References, Formatting, Data Input - IF Formulas, Nested IFs, IF with AND/OR - COUNTIFS, SUMIFS, AVERAGEIFS - Lookup Functions (VLOOKUP, XLOOKUP, XMATCH) - INDEX/MATCH for dynamic searches - TEXT Functions for string manipulations - INDIRECT and OFFSET for dynamic references - Date/Time, Math Functions, FILTER function Main Tasks: 1. Apply IF formulas to classify student grades. 2. Use COUNTIFS to count students scoring above 60. 3. Use VLOOKUP to find a product price from sales data. 4. Apply XLOOKUP to fetch employee salaries dynamically. 5. Format and analyze date of joining in Employee data. 6. Use FILTER function to extract students with grades above 80. Deliverable: Complete the given worksheets by applying the required formulas in respective sheets.
A5: Essential Tasks
A6: Relative & Absolute Cell References, Formatting, and Data Input
A7: Enter and format data (bold, italic, currency, date, custom formats).
A8: Use absolute ($A$1) and relative (A1) references in formulas.
A10: Using IF Formula & Nesting IF Formulas
A11: Classify students' grades based on their scores.
A12: Compute discounts for sales based on price thresholds.
A14: Using IF with AND/OR Formulas
A15: Identify students who scored above 80 in both Math & Science using IF(AND(...)).
A16: Determine whether a product is eligible for discount using IF(OR(...)).
... A56: Extract a list of top-performing students based on scores.

Sheet Students Grade
A1: Student ID | B1: Name | C1: Math | D1: Science | E1: English | F1: Enrollment Date | G1: Grade Classification | H1: Math > 50? | I1: Math & Science > 80? | J1: Average Score | K1: Average > 60? | L1: First Name | M1: UPPER Name | N1: lower Name | O1: Enrollment Year
A2: 1001 | B2: Student 1 | C2: 61 | D2: 48 | E2: 76 | F2: 43101 | G2: =IF(AVERAGE(C2:E2)>=90,"A+",IF(AVERAGE(C2:E2)>=80,"A",IF(AVERAGE(C2:E2)>=70,"B",IF(AVERAGE(C2:E2)>=60,"C",IF(AVERAGE(C2:E2)>=50,"D","F"))))) -> C | H2: =IF(C2>50,"Yes","No") -> Yes | I2: =IF(AND(C2>80,D2>80),"Yes","No") -> No | J2: =AVERAGE(C2:E2) -> 61.666667 | K2: =IF(J2>60,"Yes","No") -> Yes | L2: =LEFT(B2,FIND(" ",B2&" ")-1) -> Student | M2: =UPPER(B2) -> STUDENT 1 | N2: =LOWER(B2) -> student 1 | O2: =YEAR(F2) -> 2018
A3: 1002 | B3: Student 2 | C3: 78 | D3: 76 | E3: 70 | F3: 43281 | G3: =IF(AVERAGE(C3:E3)>=90,"A+",IF(AVERAGE(C3:E3)>=80,"A",IF(AVERAGE(C3:E3)>=70,"B",IF(AVERAGE(C3:E3)>=60,"C",IF(AVERAGE(C3:E3)>=50,"D","F"))))) -> B | H3: =IF(C3>50,"Yes","No") -> Yes | I3: =IF(AND(C3>80,D3>80),"Yes","No") -> No | J3: =AVERAGE(C3:E3) -> 74.666667 | K3: =IF(J3>60,"Yes","No") -> Yes | L3: =LEFT(B3,FIND(" ",B3&" ")-1) -> Student | M3: =UPPER(B3) -> STUDENT 2 | N3: =LOWER(B3) -> student 2 | O3: =YEAR(F3) -> 2018
A4: 1003 | B4: Student 3 | C4: 97 | D4: 60 | E4: 51 | F4: 43461 | G4: =IF(AVERAGE(C4:E4)>=90,"A+",IF(AVERAGE(C4:E4)>=80,"A",IF(AVERAGE(C4:E4)>=70,"B",IF(AVERAGE(C4:E4)>=60,"C",IF(AVERAGE(C4:E4)>=50,"D","F"))))) -> C | H4: =IF(C4>50,"Yes","No") -> Yes | I4: =IF(AND(C4>80,D4>80),"Yes","No") -> No | J4: =AVERAGE(C4:E4) -> 69.333333 | K4: =IF(J4>60,"Yes","No") -> Yes | L4: =LEFT(B4,FIND(" ",B4&" ")-1) -> Student | M4: =UPPER(B4) -> STUDENT 3 | N4: =LOWER(B4) -> student 3 | O4: =YEAR(F4) -> 2018
A5: 1004 | B5: Student 4 | C5: 74 | D5: 55 | E5: 46 | F5: 43641 | G5: =IF(AVERAGE(C5:E5)>=90,"A+",IF(AVERAGE(C5:E5)>=80,"A",IF(AVERAGE(C5:E5)>=70,"B",IF(AVERAGE(C5:E5)>=60,"C",IF(AVERAGE(C5:E5)>=50,"D","F"))))) -> D | H5: =IF(C5>50,"Yes","No") -> Yes | I5: =IF(AND(C5>80,D5>80),"Yes","No") -> No | J5: =AVERAGE(C5:E5) -> 58.333333 | K5: =IF(J5>60,"Yes","No") -> No | L5: =LEFT(B5,FIND(" ",B5&" ")-1) -> Student | M5: =UPPER(B5) -> STUDENT 4 | N5: =LOWER(B5) -> student 4 | O5: =YEAR(F5) -> 2019
A6: 1005 | B6: Student 5 | C6: 68 | D6: 74 | E6: 84 | F6: 43821 | G6: =IF(AVERAGE(C6:E6)>=90,"A+",IF(AVERAGE(C6:E6)>=80,"A",IF(AVERAGE(C6:E6)>=70,"B",IF(AVERAGE(C6:E6)>=60,"C",IF(AVERAGE(C6:E6)>=50,"D","F"))))) -> B | H6: =IF(C6>50,"Yes","No") -> Yes | I6: =IF(AND(C6>80,D6>80),"Yes","No") -> No | J6: =AVERAGE(C6:E6) -> 75.333333 | K6: =IF(J6>60,"Yes","No") -> Yes | L6: =LEFT(B6,FIND(" ",B6&" ")-1) -> Student | M6: =UPPER(B6) -> STUDENT 5 | N6: =LOWER(B6) -> student 5 | O6: =YEAR(F6) -> 2019
A7: 1006 | B7: Student 6 | C7: 80 | D7: 70 | E7: 65 | F7: 44001 | G7: =IF(AVERAGE(C7:E7)>=90,"A+",IF(AVERAGE(C7:E7)>=80,"A",IF(AVERAGE(C7:E7)>=70,"B",IF(AVERAGE(C7:E7)>=60,"C",IF(AVERAGE(C7:E7)>=50,"D","F"))))) -> B | H7: =IF(C7>50,"Yes","No") -> Yes | I7: =IF(AND(C7>80,D7>80),"Yes","No") -> No | J7: =AVERAGE(C7:E7) -> 71.666667 | K7: =IF(J7>60,"Yes","No") -> Yes | L7: =LEFT(B7,FIND(" ",B7&" ")-1) -> Student | M7: =UPPER(B7) -> STUDENT 6 | N7: =LOWER(B7) -> student 6 | O7: =YEAR(F7) -> 2020
A8: 1007 | B8: Student 7 | C8: 75 | D8: 47 | E8: 78 | F8: 44181 | G8: =IF(AVERAGE(C8:E8)>=90,"A+",IF(AVERAGE(C8:E8)>=80,"A",IF(AVERAGE(C8:E8)>=70,"B",IF(AVERAGE(C8:E8)>=60,"C",IF(AVERAGE(C8:E8)>=50,"D","F"))))) -> C | H8: =IF(C8>50,"Yes","No") -> Yes | I8: =IF(AND(C8>80,D8>80),"Yes","No") -> No | J8: =AVERAGE(C8:E8) -> 66.666667 | K8: =IF(J8>60,"Yes","No") -> Yes | L8: =LEFT(B8,FIND(" ",B8&" ")-1) -> Student | M8: =UPPER(B8) -> STUDENT 7 | N8: =LOWER(B8) -> student 7 | O8: =YEAR(F8) -> 2020
A9: 1008 | B9: Student 8 | C9: 94 | D9: 67 | E9: 64 | F9: 44361 | G9: =IF(AVERAGE(C9:E9)>=90,"A+",IF(AVERAGE(C9:E9)>=80,"A",IF(AVERAGE(C9:E9)>=70,"B",IF(AVERAGE(C9:E9)>=60,"C",IF(AVERAGE(C9:E9)>=50,"D","F"))))) -> B | H9: =IF(C9>50,"Yes","No") -> Yes | I9: =IF(AND(C9>80,D9>80),"Yes","No") -> No | J9: =AVERAGE(C9:E9) -> 75 | K9: =IF(J9>60,"Yes","No") -> Yes | L9: =LEFT(B9,FIND(" ",B9&" ")-1) -> Student | M9: =UPPER(B9) -> STUDENT 8 | N9: =LOWER(B9) -> student 8 | O9: =YEAR(F9) -> 2021
A10: 1009 | B10: Student 9 | C10: 41 | D10: 75 | E10: 56 | F10: 44541 | G10: =IF(AVERAGE(C10:E10)>=90,"A+",IF(AVERAGE(C10:E10)>=80,"A",IF(AVERAGE(C10:E10)>=70,"B",IF(AVERAGE(C10:E10)>=60,"C",IF(AVERAGE(C10:E10)>=50,"D","F"))))) -> D | H10: =IF(C10>50,"Yes","No") -> No | I10: =IF(AND(C10>80,D10>80),"Yes","No") -> No | J10: =AVERAGE(C10:E10) -> 57.333333 | K10: =IF(J10>60,"Yes","No") -> No | L10: =LEFT(B10,FIND(" ",B10&" ")-1) -> Student | M10: =UPPER(B10) -> STUDENT 9 | N10: =LOWER(B10) -> student 9 | O10: =YEAR(F10) -> 2021
A11: 1010 | B11: Student 10 | C11: 98 | D11: 54 | E11: 58 | F11: 44721 | G11: =IF(AVERAGE(C11:E11)>=90,"A+",IF(AVERAGE(C11:E11)>=80,"A",IF(AVERAGE(C11:E11)>=70,"B",IF(AVERAGE(C11:E11)>=60,"C",IF(AVERAGE(C11:E11)>=50,"D","F"))))) -> B | H11: =IF(C11>50,"Yes","No") -> Yes | I11: =IF(AND(C11>80,D11>80),"Yes","No") -> No | J11: =AVERAGE(C11:E11) -> 70 | K11: =IF(J11>60,"Yes","No") -> Yes | L11: =LEFT(B11,FIND(" ",B11&" ")-1) -> Student | M11: =UPPER(B11) -> STUDENT 10 | N11: =LOWER(B11) -> student 10 | O11: =YEAR(F11) -> 2022
A12: 1011 | B12: Student 11 | C12: 73 | D12: 79 | E12: 53 | F12: 44901 | G12: =IF(AVERAGE(C12:E12)>=90,"A+",IF(AVERAGE(C12:E12)>=80,"A",IF(AVERAGE(C12:E12)>=70,"B",IF(AVERAGE(C12:E12)>=60,"C",IF(AVERAGE(C12:E12)>=50,"D","F"))))) -> C | H12: =IF(C12>50,"Yes","No") -> Yes | I12: =IF(AND(C12>80,D12>80),"Yes","No") -> No | J12: =AVERAGE(C12:E12) -> 68.333333 | K12: =IF(J12>60,"Yes","No") -> Yes | L12: =LEFT(B12,FIND(" ",B12&" ")-1) -> Student | M12: =UPPER(B12) -> STUDENT 11 | N12: =LOWER(B12) -> student 11 | O12: =YEAR(F12) -> 2022
A13: 1012 | B13: Student 12 | C13: 85 | D13: 89 | E13: 79 | F13: 45081 | G13: =IF(AVERAGE(C13:E13)>=90,"A+",IF(AVERAGE(C13:E13)>=80,"A",IF(AVERAGE(C13:E13)>=70,"B",IF(AVERAGE(C13:E13)>=60,"C",IF(AVERAGE(C13:E13)>=50,"D","F"))))) -> A | H13: =IF(C13>50,"Yes","No") -> Yes | I13: =IF(AND(C13>80,D13>80),"Yes","No") -> Yes | J13: =AVERAGE(C13:E13) -> 84.333333 | K13: =IF(J13>60,"Yes","No") -> Yes | L13: =LEFT(B13,FIND(" ",B13&" ")-1) -> Student | M13: =UPPER(B13) -> STUDENT 12 | N13: =LOWER(B13) -> student 12 | O13: =YEAR(F13) -> 2023
... A21: 1020 | B21: Student 20 | C21: 83 | D21: 92 | E21: 55 | F21: 46521 | G21: =IF(AVERAGE(C21:E21)>=90,"A+",IF(AVERAGE(C21:E21)>=80,"A",IF(AVERAGE(C21:E21)>=70,"B",IF(AVERAGE(C21:E21)>=60,"C",IF(AVERAGE(C21:E21)>=50,"D","F"))))) -> B | H21: =IF(C21>50,"Yes","No") -> Yes | I21: =IF(AND(C21>80,D21>80),"Yes","No") -> Yes | J21: =AVERAGE(C21:E21) -> 76.666667 | K21: =IF(J21>60,"Yes","No") -> Yes | L21: =LEFT(B21,FIND(" ",B21&" ")-1) -> Student | M21: =UPPER(B21) -> STUDENT 20 | N21: =LOWER(B21) -> student 20 | O21: =YEAR(F21) -> 2027

Sheet Sales Data
A1: Sales ID | B1: Product | C1: Region | D1: Salesperson | E1: Amount | F1: Date | G1: Discount % | H1: Discount Amount | I1: Net Sales | J1: Discount Eligible? | K1: Month | L1: Year | M1: Quarter | N1: GST Amount | O1: GST Rate | P1: 0.18
A2: 2001 | B2: Keyboard | C2: South | D2: Person 1 | E2: 7048 | F2: 44927 | G2: =IF(E2>=40000,15%,IF(E2>=25000,10%,IF(E2>=10000,5%,0%))) -> 0 | H2: =E2*G2 -> 0 | I2: =E2-H2 -> 7048 | J2: =IF(OR(E2>=25000,C2="West"),"Eligible","Not Eligible") -> Not Eligible | K2: =TEXT(F2,"mmmm") -> January | L2: =YEAR(F2) -> 2023 | M2: ="Q"&ROUNDUP(MONTH(F2)/3,0) -> Q1 | N2: =E2*$P$1 -> 1268.64
A3: 2002 | B3: Printer | C3: West | D3: Person 2 | E3: 17428 | F3: 44942 | G3: =IF(E3>=40000,15%,IF(E3>=25000,10%,IF(E3>=10000,5%,0%))) -> 0.05 | H3: =E3*G3 -> 871.4 | I3: =E3-H3 -> 16556.6 | J3: =IF(OR(E3>=25000,C3="West"),"Eligible","Not Eligible") -> Eligible | K3: =TEXT(F3,"mmmm") -> January | L3: =YEAR(F3) -> 2023 | M3: ="Q"&ROUNDUP(MONTH(F3)/3,0) -> Q1 | N3: =E3*$P$1 -> 3137.04
A4: 2003 | B4: Mouse | C4: South | D4: Person 3 | E4: 23672 | F4: 44957 | G4: =IF(E4>=40000,15%,IF(E4>=25000,10%,IF(E4>=10000,5%,0%))) -> 0.05 | H4: =E4*G4 -> 1183.6 | I4: =E4-H4 -> 22488.4 | J4: =IF(OR(E4>=25000,C4="West"),"Eligible","Not Eligible") -> Not Eligible | K4: =TEXT(F4,"mmmm") -> January | L4: =YEAR(F4) -> 2023 | M4: ="Q"&ROUNDUP(MONTH(F4)/3,0) -> Q1 | N4: =E4*$P$1 -> 4260.96
A5: 2004 | B5: Printer | C5: East | D5: Person 4 | E5: 5264 | F5: 44972 | G5: =IF(E5>=40000,15%,IF(E5>=25000,10%,IF(E5>=10000,5%,0%))) -> 0 | H5: =E5*G5 -> 0 | I5: =E5-H5 -> 5264 | J5: =IF(OR(E5>=25000,C5="West"),"Eligible","Not Eligible") -> Not Eligible | K5: =TEXT(F5,"mmmm") -> February | L5: =YEAR(F5) -> 2023 | M5: ="Q"&ROUNDUP(MONTH(F5)/3,0) -> Q1 | N5: =E5*$P$1 -> 947.52
A6: 2005 | B6: Keyboard | C6: North | D6: Person 5 | E6: 43388 | F6: 44987 | G6: =IF(E6>=40000,15%,IF(E6>=25000,10%,IF(E6>=10000,5%,0%))) -> 0.15 | H6: =E6*G6 -> 6508.2 | I6: =E6-H6 -> 36879.8 | J6: =IF(OR(E6>=25000,C6="West"),"Eligible","Not Eligible") -> Eligible | K6: =TEXT(F6,"mmmm") -> March | L6: =YEAR(F6) -> 2023 | M6: ="Q"&ROUNDUP(MONTH(F6)/3,0) -> Q1 | N6: =E6*$P$1 -> 7809.84
A7: 2006 | B7: Mouse | C7: North | D7: Person 6 | E7: 19757 | F7: 45002 | G7: =IF(E7>=40000,15%,IF(E7>=25000,10%,IF(E7>=10000,5%,0%))) -> 0.05 | H7: =E7*G7 -> 987.85 | I7: =E7-H7 -> 18769.15 | J7: =IF(OR(E7>=25000,C7="West"),"Eligible","Not Eligible") -> Not Eligible | K7: =TEXT(F7,"mmmm") -> March | L7: =YEAR(F7) -> 2023 | M7: ="Q"&ROUNDUP(MONTH(F7)/3,0) -> Q1 | N7: =E7*$P$1 -> 3556.26
A8: 2007 | B8: Mouse | C8: East | D8: Person 7 | E8: 32058 | F8: 45017 | G8: =IF(E8>=40000,15%,IF(E8>=25000,10%,IF(E8>=10000,5%,0%))) -> 0.1 | H8: =E8*G8 -> 3205.8 | I8: =E8-H8 -> 28852.2 | J8: =IF(OR(E8>=25000,C8="West"),"Eligible","Not Eligible") -> Eligible | K8: =TEXT(F8,"mmmm") -> April | L8: =YEAR(F8) -> 2023 | M8: ="Q"&ROUNDUP(MONTH(F8)/3,0) -> Q2 | N8: =E8*$P$1 -> 5770.44
A9: 2008 | B9: Keyboard | C9: East | D9: Person 8 | E9: 46429 | F9: 45032 | G9: =IF(E9>=40000,15%,IF(E9>=25000,10%,IF(E9>=10000,5%,0%))) -> 0.15 | H9: =E9*G9 -> 6964.35 | I9: =E9-H9 -> 39464.65 | J9: =IF(OR(E9>=25000,C9="West"),"Eligible","Not Eligible") -> Eligible | K9: =TEXT(F9,"mmmm") -> April | L9: =YEAR(F9) -> 2023 | M9: ="Q"&ROUNDUP(MONTH(F9)/3,0) -> Q2 | N9: =E9*$P$1 -> 8357.22
A10: 2009 | B10: Printer | C10: East | D10: Person 9 | E10: 19746 | F10: 45047 | G10: =IF(E10>=40000,15%,IF(E10>=25000,10%,IF(E10>=10000,5%,0%))) -> 0.05 | H10: =E10*G10 -> 987.3 | I10: =E10-H10 -> 18758.7 | J10: =IF(OR(E10>=25000,C10="West"),"Eligible","Not Eligible") -> Not Eligible | K10: =TEXT(F10,"mmmm") -> May | L10: =YEAR(F10) -> 2023 | M10: ="Q"&ROUNDUP(MONTH(F10)/3,0) -> Q2 | N10: =E10*$P$1 -> 3554.28
A11: 2010 | B11: Keyboard | C11: South | D11: Person 10 | E11: 35185 | F11: 45062 | G11: =IF(E11>=40000,15%,IF(E11>=25000,10%,IF(E11>=10000,5%,0%))) -> 0.1 | H11: =E11*G11 -> 3518.5 | I11: =E11-H11 -> 31666.5 | J11: =IF(OR(E11>=25000,C11="West"),"Eligible","Not Eligible") -> Eligible | K11: =TEXT(F11,"mmmm") -> May | L11: =YEAR(F11) -> 2023 | M11: ="Q"&ROUNDUP(MONTH(F11)/3,0) -> Q2 | N11: =E11*$P$1 -> 6333.3
A12: 2011 | B12: Keyboard | C12: East | D12: Person 11 | E12: 33920 | F12: 45077 | G12: =IF(E12>=40000,15%,IF(E12>=25000,10%,IF(E12>=10000,5%,0%))) -> 0.1 | H12: =E12*G12 -> 3392 | I12: =E12-H12 -> 30528 | J12: =IF(OR(E12>=25000,C12="West"),"Eligible","Not Eligible") -> Eligible | K12: =TEXT(F12,"mmmm") -> May | L12: =YEAR(F12) -> 2023 | M12: ="Q"&ROUNDUP(MONTH(F12)/3,0) -> Q2 | N12: =E12*$P$1 -> 6105.6
A13: 2012 | B13: Monitor | C13: North | D13: Person 12 | E13: 35611 | F13: 45092 | G13: =IF(E13>=40000,15%,IF(E13>=25000,10%,IF(E13>=10000,5%,0%))) -> 0.1 | H13: =E13*G13 -> 3561.1 | I13: =E13-H13 -> 32049.9 | J13: =IF(OR(E13>=25000,C13="West"),"Eligible","Not Eligible") -> Eligible | K13: =TEXT(F13,"mmmm") -> June | L13: =YEAR(F13) -> 2023 | M13: ="Q"&ROUNDUP(MONTH(F13)/3,0) -> Q2 | N13: =E13*$P$1 -> 6409.98
... A21: 2020 | B21: Printer | C21: West | D21: Person 20 | E21: 33953 | F21: 45212 | G21: =IF(E21>=40000,15%,IF(E21>=25000,10%,IF(E21>=10000,5%,0%))) -> 0.1 | H21: =E21*G21 -> 3395.3 | I21: =E21-H21 -> 30557.7 | J21: =IF(OR(E21>=25000,C21="West"),"Eligible","Not Eligible") -> Eligible | K21: =TEXT(F21,"mmmm") -> October | L21: =YEAR(F21) -> 2023 | M21: ="Q"&ROUNDUP(MONTH(F21)/3,0) -> Q4 | N21: =E21*$P$1 -> 6111.54

Sheet Employee Data
A1: Employee ID | B1: Name | C1: Department | D1: Salary | E1: Joining Date | F1: Joining Year | G1: Joining Month | H1: Years of Service | I1: Salary Band
A2: 3001 | B2: Employee 1 | C2: Finance | D2: 86766 | E2: 42005 | F2: =YEAR(E2) -> 2015 | G2: =TEXT(E2,"mmmm") -> January | H2: =IF(E2>TODAY(),0,DATEDIF(E2,TODAY(),"Y")) -> 11 | I2: =IF(D2>=100000,"High",IF(D2>=60000,"Medium","Entry")) -> Medium
A3: 3002 | B3: Employee 2 | C3: Finance | D3: 31943 | E3: 42255 | F3: =YEAR(E3) -> 2015 | G3: =TEXT(E3,"mmmm") -> September | H3: =IF(E3>TODAY(),0,DATEDIF(E3,TODAY(),"Y")) -> 11 | I3: =IF(D3>=100000,"High",IF(D3>=60000,"Medium","Entry")) -> Entry
A4: 3003 | B4: Employee 3 | C4: HR | D4: 63374 | E4: 42505 | F4: =YEAR(E4) -> 2016 | G4: =TEXT(E4,"mmmm") -> May | H4: =IF(E4>TODAY(),0,DATEDIF(E4,TODAY(),"Y")) -> 10 | I4: =IF(D4>=100000,"High",IF(D4>=60000,"Medium","Entry")) -> Medium
A5: 3004 | B5: Employee 4 | C5: Finance | D5: 109972 | E5: 42755 | F5: =YEAR(E5) -> 2017 | G5: =TEXT(E5,"mmmm") -> January | H5: =IF(E5>TODAY(),0,DATEDIF(E5,TODAY(),"Y")) -> 9 | I5: =IF(D5>=100000,"High",IF(D5>=60000,"Medium","Entry")) -> High
A6: 3005 | B6: Employee 5 | C6: IT | D6: 54149 | E6: 43005 | F6: =YEAR(E6) -> 2017 | G6: =TEXT(E6,"mmmm") -> September | H6: =IF(E6>TODAY(),0,DATEDIF(E6,TODAY(),"Y")) -> 9 | I6: =IF(D6>=100000,"High",IF(D6>=60000,"Medium","Entry")) -> Entry
A7: 3006 | B7: Employee 6 | C7: IT | D7: 78689 | E7: 43255 | F7: =YEAR(E7) -> 2018 | G7: =TEXT(E7,"mmmm") -> June | H7: =IF(E7>TODAY(),0,DATEDIF(E7,TODAY(),"Y")) -> 8 | I7: =IF(D7>=100000,"High",IF(D7>=60000,"Medium","Entry")) -> Medium
A8: 3007 | B8: Employee 7 | C8: Marketing | D8: 35960 | E8: 43505 | F8: =YEAR(E8) -> 2019 | G8: =TEXT(E8,"mmmm") -> February | H8: =IF(E8>TODAY(),0,DATEDIF(E8,TODAY(),"Y")) -> 7 | I8: =IF(D8>=100000,"High",IF(D8>=60000,"Medium","Entry")) -> Entry
A9: 3008 | B9: Employee 8 | C9: IT | D9: 91659 | E9: 43755 | F9: =YEAR(E9) -> 2019 | G9: =TEXT(E9,"mmmm") -> October | H9: =IF(E9>TODAY(),0,DATEDIF(E9,TODAY(),"Y")) -> 6 | I9: =IF(D9>=100000,"High",IF(D9>=60000,"Medium","Entry")) -> Medium
A10: 3009 | B10: Employee 9 | C10: IT | D10: 90423 | E10: 44005 | F10: =YEAR(E10) -> 2020 | G10: =TEXT(E10,"mmmm") -> June | H10: =IF(E10>TODAY(),0,DATEDIF(E10,TODAY(),"Y")) -> 6 | I10: =IF(D10>=100000,"High",IF(D10>=60000,"Medium","Entry")) -> Medium
A11: 3010 | B11: Employee 10 | C11: HR | D11: 107877 | E11: 44255 | F11: =YEAR(E11) -> 2021 | G11: =TEXT(E11,"mmmm") -> February | H11: =IF(E11>TODAY(),0,DATEDIF(E11,TODAY(),"Y")) -> 5 | I11: =IF(D11>=100000,"High",IF(D11>=60000,"Medium","Entry")) -> High
A12: 3011 | B12: Employee 11 | C12: Finance | D12: 107634 | E12: 44505 | F12: =YEAR(E12) -> 2021 | G12: =TEXT(E12,"mmmm") -> November | H12: =IF(E12>TODAY(),0,DATEDIF(E12,TODAY(),"Y")) -> 4 | I12: =IF(D12>=100000,"High",IF(D12>=60000,"Medium","Entry")) -> High
A13: 3012 | B13: Employee 12 | C13: Finance | D13: 35226 | E13: 44755 | F13: =YEAR(E13) -> 2022 | G13: =TEXT(E13,"mmmm") -> July | H13: =IF(E13>TODAY(),0,DATEDIF(E13,TODAY(),"Y")) -> 4 | I13: =IF(D13>=100000,"High",IF(D13>=60000,"Medium","Entry")) -> Entry
... A21: 3020 | B21: Employee 20 | C21: Marketing | D21: 99924 | E21: 46755 | F21: =YEAR(E21) -> 2028 | G21: =TEXT(E21,"mmmm") -> January | H21: =IF(E21>TODAY(),0,DATEDIF(E21,TODAY(),"Y")) -> 0 | I21: =IF(D21>=100000,"High",IF(D21>=60000,"Medium","Entry")) -> Medium

Sheet Analysis & Solutions
A1: PR. 1 FUNDAMENTAL BOOSTER — COMPLETED ANALYSIS
A2: All required tasks are demonstrated below using formulas linked to the supplied datasets.
A4: 1. IF / NESTED IF — Student Grade Classification
A5: Student ID | B5: Name | C5: Average Score | D5: Grade
A6: ='Students Grade'!A2 -> 1001 | B6: ='Students Grade'!B2 -> Student 1 | C6: =AVERAGE('Students Grade'!C2:'Students Grade'!E2) -> 61.666667 | D6: =IF(C6>=90,"A+",IF(C6>=80,"A",IF(C6>=70,"B",IF(C6>=60,"C",IF(C6>=50,"D","F"))))) -> C
A7: ='Students Grade'!A3 -> 1002 | B7: ='Students Grade'!B3 -> Student 2 | C7: =AVERAGE('Students Grade'!C3:'Students Grade'!E3) -> 74.666667 | D7: =IF(C7>=90,"A+",IF(C7>=80,"A",IF(C7>=70,"B",IF(C7>=60,"C",IF(C7>=50,"D","F"))))) -> B
A8: ='Students Grade'!A4 -> 1003 | B8: ='Students Grade'!B4 -> Student 3 | C8: =AVERAGE('Students Grade'!C4:'Students Grade'!E4) -> 69.333333 | D8: =IF(C8>=90,"A+",IF(C8>=80,"A",IF(C8>=70,"B",IF(C8>=60,"C",IF(C8>=50,"D","F"))))) -> C
A9: ='Students Grade'!A5 -> 1004 | B9: ='Students Grade'!B5 -> Student 4 | C9: =AVERAGE('Students Grade'!C5:'Students Grade'!E5) -> 58.333333 | D9: =IF(C9>=90,"A+",IF(C9>=80,"A",IF(C9>=70,"B",IF(C9>=60,"C",IF(C9>=50,"D","F"))))) -> D
A10: ='Students Grade'!A6 -> 1005 | B10: ='Students Grade'!B6 -> Student 5 | C10: =AVERAGE('Students Grade'!C6:'Students Grade'!E6) -> 75.333333 | D10: =IF(C10>=90,"A+",IF(C10>=80,"A",IF(C10>=70,"B",IF(C10>=60,"C",IF(C10>=50,"D","F"))))) -> B
A11: ='Students Grade'!A7 -> 1006 | B11: ='Students Grade'!B7 -> Student 6 | C11: =AVERAGE('Students Grade'!C7:'Students Grade'!E7) -> 71.666667 | D11: =IF(C11>=90,"A+",IF(C11>=80,"A",IF(C11>=70,"B",IF(C11>=60,"C",IF(C11>=50,"D","F"))))) -> B
A12: ='Students Grade'!A8 -> 1007 | B12: ='Students Grade'!B8 -> Student 7 | C12: =AVERAGE('Students Grade'!C8:'Students Grade'!E8) -> 66.666667 | D12: =IF(C12>=90,"A+",IF(C12>=80,"A",IF(C12>=70,"B",IF(C12>=60,"C",IF(C12>=50,"D","F"))))) -> C
A13: ='Students Grade'!A9 -> 1008 | B13: ='Students Grade'!B9 -> Student 8 | C13: =AVERAGE('Students Grade'!C9:'Students Grade'!E9) -> 75 | D13: =IF(C13>=90,"A+",IF(C13>=80,"A",IF(C13>=70,"B",IF(C13>=60,"C",IF(C13>=50,"D","F"))))) -> B
A14: ='Students Grade'!A10 -> 1009 | B14: ='Students Grade'!B10 -> Student 9 | C14: =AVERAGE('Students Grade'!C10:'Students Grade'!E10) -> 57.333333 | D14: =IF(C14>=90,"A+",IF(C14>=80,"A",IF(C14>=70,"B",IF(C14>=60,"C",IF(C14>=50,"D","F"))))) -> D
A15: ='Students Grade'!A11 -> 1010 | B15: ='Students Grade'!B11 -> Student 10 | C15: =AVERAGE('Students Grade'!C11:'Students Grade'!E11) -> 70 | D15: =IF(C15>=90,"A+",IF(C15>=80,"A",IF(C15>=70,"B",IF(C15>=60,"C",IF(C15>=50,"D","F"))))) -> B
A16: ='Students Grade'!A12 -> 1011 | B16: ='Students Grade'!B12 -> Student 11 | C16: =AVERAGE('Students Grade'!C12:'Students Grade'!E12) -> 68.333333 | D16: =IF(C16>=90,"A+",IF(C16>=80,"A",IF(C16>=70,"B",IF(C16>=60,"C",IF(C16>=50,"D","F"))))) -> C
A17: ='Students Grade'!A13 -> 1012 | B17: ='Students Grade'!B13 -> Student 12 | C17: =AVERAGE('Students Grade'!C13:'Students Grade'!E13) -> 84.333333 | D17: =IF(C17>=90,"A+",IF(C17>=80,"A",IF(C17>=70,"B",IF(C17>=60,"C",IF(C17>=50,"D","F"))))) -> A
... A25: ='Students Grade'!A21 -> 1020 | B25: ='Students Grade'!B21 -> Student 20 | C25: =AVERAGE('Students Grade'!C21:'Students Grade'!E21) -> 76.666667 | D25: =IF(C25>=90,"A+",IF(C25>=80,"A",IF(C25>=70,"B",IF(C25>=60,"C",IF(C25>=50,"D","F"))))) -> B
A27: 2. COUNTIFS — Students Scoring Above 60
A28: Count of students with Math > 60 | B28: =COUNTIFS('Students Grade'!$C$2:$C$21,">60") -> 19
A29: Count of students with Science > 60 | B29: =COUNTIFS('Students Grade'!$D$2:$D$21,">60") -> 11
A30: Count of students with Math > 50 | B30: =COUNTIFS('Students Grade'!$C$2:$C$21,">50") -> 19
A31: 3. VLOOKUP — Product Reference Amount
A32: Product | B32: Reference Amount (Average Sales Amount) | C32: VLOOKUP Result | E32: Product Code | F32: Product | G32: List Price (sample input)
A33: Keyboard | B33: =AVERAGEIF('Sales Data'!$B$2:$B$21,A33,'Sales Data'!$E$2:$E$21) -> 33194 | C33: =VLOOKUP(A33,$A$33:$B$37,2,FALSE) -> 33194 | E33: P-101 | F33: Keyboard | G33: 1200
A34: Laptop | B34: =AVERAGEIF('Sales Data'!$B$2:$B$21,A34,'Sales Data'!$E$2:$E$21) -> 12840.333 | C34: =VLOOKUP(A34,$A$33:$B$37,2,FALSE) -> 12840.333 | E34: P-102 | F34: Laptop | G34: 45000
A35: Monitor | B35: =AVERAGEIF('Sales Data'!$B$2:$B$21,A35,'Sales Data'!$E$2:$E$21) -> 38547.667 | C35: =VLOOKUP(A35,$A$33:$B$37,2,FALSE) -> 38547.667 | E35: P-103 | F35: Monitor | G35: 9500
A36: Mouse | B36: =AVERAGEIF('Sales Data'!$B$2:$B$21,A36,'Sales Data'!$E$2:$E$21) -> 22240 | C36: =VLOOKUP(A36,$A$33:$B$37,2,FALSE) -> 22240 | E36: P-104 | F36: Mouse | G36: 450
A37: Printer | B37: =AVERAGEIF('Sales Data'!$B$2:$B$21,A37,'Sales Data'!$E$2:$E$21) -> 19097.75 | C37: =VLOOKUP(A37,$A$33:$B$37,2,FALSE) -> 19097.75 | E37: P-105 | F37: Printer | G37: 7800
A39: Selected Product | B39: Keyboard | E39: Selected Product Code | F39: P-104
A40: VLOOKUP Result | B40: =VLOOKUP(B39,$A$33:$B$37,2,FALSE) -> 33194 | E40: VLOOKUP Price | F40: =VLOOKUP(F39,$E$33:$G$37,3,FALSE) -> 450
A42: 4. SUMIFS / AVERAGEIFS — Sales & Student Analysis
A43: Region | B43: Product | C43: Total Sales
A44: East | B44: Keyboard | C44: =SUMIFS('Sales Data'!$E$2:$E$21,'Sales Data'!$C$2:$C$21,A44,'Sales Data'!$B$2:$B$21,B44) -> 80349
A46: Average Math score where Math > 60 | B46: =AVERAGEIFS('Students Grade'!$C$2:$C$21,'Students Grade'!$C$2:$C$21,">60") -> 82.263158
A48: 5. VLOOKUP — Student Name by ID
A49: Student ID | B49: Student Name
A50: 1001 | B50: =VLOOKUP(A50,'Students Grade'!$A$2:$B$21,2,FALSE) -> Student 1
A52: 6. INDEX / MATCH — Dynamic Sales & Employee Search
A53: Salesperson | B53: Selected Month | C53: Sales Value
A54: Person 10 | B54: 45047 | C54: =INDEX('Sales Data'!$E$2:$E$21,MATCH(1,INDEX(('Sales Data'!$D$2:$D$21=A54)*(MONTH('Sales Data'!$F$2:$F$21)=MONTH(B54))*(YEAR('Sales Data'!$F$2:$F$21)=YEAR(B54)),0),0)) -> 35185
A57: Employee ID | B57: Field | C57: Result
A58: 3005 | B58: Department | C58: =INDEX('Employee Data'!$A$2:$I$21,MATCH(A58,'Employee Data'!$A$2:$A$21,0),MATCH(B58,'Employee Data'!$A$1:$I$1,0)) -> IT
A59: 3005 | B59: Salary | C59: =INDEX('Employee Data'!$A$2:$I$21,MATCH(A59,'Employee Data'!$A$2:$A$21,0),MATCH(B59,'Employee Data'!$A$1:$I$1,0)) -> 54149
A61: 7. XLOOKUP — Flexible Employee Salary & Salesperson Performance
A62: Employee ID | B62: XLOOKUP Salary
A63: 3005 | B63: =_xlfn.XLOOKUP(A63,'Employee Data'!$A$2:$A$21,'Employee Data'!$D$2:$D$21,"Not Found") -> 54149
A66: Salesperson | B66: Total Sales
A67: Person 1 | B67: =SUMIF('Sales Data'!$D$2:$D$21,A67,'Sales Data'!$E$2:$E$21) -> 7048
A68: Person 10 | B68: =SUMIF('Sales Data'!$D$2:$D$21,A68,'Sales Data'!$E$2:$E$21) -> 35185
A69: Person 11 | B69: =SUMIF('Sales Data'!$D$2:$D$21,A69,'Sales Data'!$E$2:$E$21) -> 33920
A70: Person 12 | B70: =SUMIF('Sales Data'!$D$2:$D$21,A70,'Sales Data'!$E$2:$E$21) -> 35611
A71: Person 13 | B71: =SUMIF('Sales Data'!$D$2:$D$21,A71,'Sales Data'!$E$2:$E$21) -> 15560
A72: Person 14 | B72: =SUMIF('Sales Data'!$D$2:$D$21,A72,'Sales Data'!$E$2:$E$21) -> 7283
A73: Person 15 | B73: =SUMIF('Sales Data'!$D$2:$D$21,A73,'Sales Data'!$E$2:$E$21) -> 15678
A74: Person 16 | B74: =SUMIF('Sales Data'!$D$2:$D$21,A74,'Sales Data'!$E$2:$E$21) -> 5277
A75: Person 17 | B75: =SUMIF('Sales Data'!$D$2:$D$21,A75,'Sales Data'!$E$2:$E$21) -> 41871
A76: Person 18 | B76: =SUMIF('Sales Data'!$D$2:$D$21,A76,'Sales Data'!$E$2:$E$21) -> 38161
A77: Person 19 | B77: =SUMIF('Sales Data'!$D$2:$D$21,A77,'Sales Data'!$E$2:$E$21) -> 30436
A78: Person 2 | B78: =SUMIF('Sales Data'!$D$2:$D$21,A78,'Sales Data'!$E$2:$E$21) -> 17428
... A86: Person 9 | B86: =SUMIF('Sales Data'!$D$2:$D$21,A86,'Sales Data'!$E$2:$E$21) -> 19746
A88: Selected Salesperson | B88: Person 1
A89: XLOOKUP Performance | B89: =_xlfn.XLOOKUP(B88,$A$67:$A$86,$B$67:$B$86,"Not Found") -> 7048
A91: 8. XMATCH — Product Position in Sales List
A92: Product to Find | B92: Position in Sales Product List
A93: Keyboard | B93: =_xlfn.XMATCH(A93,'Sales Data'!$B$2:$B$21,0) -> 1
A95: 9. INDIRECT — Dynamic Range Reference
A96: Range Reference | B96: Calculated Total
A97: 'Sales Data'!E2:E21 | B97: =SUM(INDIRECT(A97)) -> 507725
A99: 10. OFFSET — Dynamic 3-Period Sales Trend
A100: Month | B100: Monthly Sales | C100: 3-Month Moving Total (OFFSET)
A101: 44927 | B101: =SUMIFS('Sales Data'!$E$2:$E$21,'Sales Data'!$F$2:$F$21,">="&A101,'Sales Data'!$F$2:$F$21,"<"&EDATE(A101,1)) -> 48148
A102: 44958 | B102: =SUMIFS('Sales Data'!$E$2:$E$21,'Sales Data'!$F$2:$F$21,">="&A102,'Sales Data'!$F$2:$F$21,"<"&EDATE(A102,1)) -> 5264
A103: 44986 | B103: =SUMIFS('Sales Data'!$E$2:$E$21,'Sales Data'!$F$2:$F$21,">="&A103,'Sales Data'!$F$2:$F$21,"<"&EDATE(A103,1)) -> 63145 | C103: =SUM(OFFSET(B103,-2,0,3,1)) -> 116557
A104: 45017 | B104: =SUMIFS('Sales Data'!$E$2:$E$21,'Sales Data'!$F$2:$F$21,">="&A104,'Sales Data'!$F$2:$F$21,"<"&EDATE(A104,1)) -> 78487 | C104: =SUM(OFFSET(B104,-2,0,3,1)) -> 146896
A105: 45047 | B105: =SUMIFS('Sales Data'!$E$2:$E$21,'Sales Data'!$F$2:$F$21,">="&A105,'Sales Data'!$F$2:$F$21,"<"&EDATE(A105,1)) -> 88851 | C105: =SUM(OFFSET(B105,-2,0,3,1)) -> 230483
A106: 45078 | B106: =SUMIFS('Sales Data'!$E$2:$E$21,'Sales Data'!$F$2:$F$21,">="&A106,'Sales Data'!$F$2:$F$21,"<"&EDATE(A106,1)) -> 51171 | C106: =SUM(OFFSET(B106,-2,0,3,1)) -> 218509
A107: 45108 | B107: =SUMIFS('Sales Data'!$E$2:$E$21,'Sales Data'!$F$2:$F$21,">="&A107,'Sales Data'!$F$2:$F$21,"<"&EDATE(A107,1)) -> 22961 | C107: =SUM(OFFSET(B107,-2,0,3,1)) -> 162983
A108: 45139 | B108: =SUMIFS('Sales Data'!$E$2:$E$21,'Sales Data'!$F$2:$F$21,">="&A108,'Sales Data'!$F$2:$F$21,"<"&EDATE(A108,1)) -> 47148 | C108: =SUM(OFFSET(B108,-2,0,3,1)) -> 121280
A109: 45170 | B109: =SUMIFS('Sales Data'!$E$2:$E$21,'Sales Data'!$F$2:$F$21,">="&A109,'Sales Data'!$F$2:$F$21,"<"&EDATE(A109,1)) -> 68597 | C109: =SUM(OFFSET(B109,-2,0,3,1)) -> 138706
A110: 45200 | B110: =SUMIFS('Sales Data'!$E$2:$E$21,'Sales Data'!$F$2:$F$21,">="&A110,'Sales Data'!$F$2:$F$21,"<"&EDATE(A110,1)) -> 33953 | C110: =SUM(OFFSET(B110,-2,0,3,1)) -> 149698
A113: 11. DATE / TIME — Joining Date Analysis
A114: Employee | B114: Joining Date | C114: Joining Year | D114: Years of Service
A115: ='Employee Data'!B2 -> Employee 1 | B115: ='Employee Data'!E2 -> 42005 | C115: =YEAR(B115) -> 2015 | D115: =IF(B115>TODAY(),0,DATEDIF(B115,TODAY(),"Y")) -> 11
A116: ='Employee Data'!B3 -> Employee 2 | B116: ='Employee Data'!E3 -> 42255 | C116: =YEAR(B116) -> 2015 | D116: =IF(B116>TODAY(),0,DATEDIF(B116,TODAY(),"Y")) -> 11
A117: ='Employee Data'!B4 -> Employee 3 | B117: ='Employee Data'!E4 -> 42505 | C117: =YEAR(B117) -> 2016 | D117: =IF(B117>TODAY(),0,DATEDIF(B117,TODAY(),"Y")) -> 10
A118: ='Employee Data'!B5 -> Employee 4 | B118: ='Employee Data'!E5 -> 42755 | C118: =YEAR(B118) -> 2017 | D118: =IF(B118>TODAY(),0,DATEDIF(B118,TODAY(),"Y")) -> 9
A119: ='Employee Data'!B6 -> Employee 5 | B119: ='Employee Data'!E6 -> 43005 | C119: =YEAR(B119) -> 2017 | D119: =IF(B119>TODAY(),0,DATEDIF(B119,TODAY(),"Y")) -> 9
A121: Days between first and last employee joining dates | B121: =MAX('Employee Data'!$E$2:$E$21)-MIN('Employee Data'!$E$2:$E$21) -> 4750
A124: 12. MATH FUNCTIONS — ROUND / CEILING / FLOOR
A125: Sales Amount | B125: ROUND | C125: CEILING | D125: FLOOR
A126: ='Sales Data'!E2 -> 7048 | B126: =ROUND(A126,-2) -> 7000 | C126: =CEILING(A126,1000) -> 8000 | D126: =FLOOR(A126,1000) -> 7000
A127: ='Sales Data'!E3 -> 17428 | B127: =ROUND(A127,-2) -> 17400 | C127: =CEILING(A127,1000) -> 18000 | D127: =FLOOR(A127,1000) -> 17000
A128: ='Sales Data'!E4 -> 23672 | B128: =ROUND(A128,-2) -> 23700 | C128: =CEILING(A128,1000) -> 24000 | D128: =FLOOR(A128,1000) -> 23000
A129: ='Sales Data'!E5 -> 5264 | B129: =ROUND(A129,-2) -> 5300 | C129: =CEILING(A129,1000) -> 6000 | D129: =FLOOR(A129,1000) -> 5000
A130: ='Sales Data'!E6 -> 43388 | B130: =ROUND(A130,-2) -> 43400 | C130: =CEILING(A130,1000) -> 44000 | D130: =FLOOR(A130,1000) -> 43000
A133: 13. FILTER — Top-Performing Students (Average Score > 80)
A134: Student ID | B134: Name | C134: Average Score
A135: {=IFERROR(_xlfn._xlws.FILTER('Students Grade'!$A$2:$B$21,'Students Grade'!$J$2:$J$21>80,"No students found"),"")} -> 1012 | B135: Student 12 | C135: {=IFERROR(_xlfn._xlws.FILTER('Students Grade'!$J$2:$J$21,'Students Grade'!$J$2:$J$21>80,"No students found"),"")} -> 84.333333
A136: 1013 | B136: Student 13 | C136: 95
A143: Note: FILTER needs Excel 2021 / Microsoft 365. The block holds up to 8 students; extra rows stay blank.
...

Sheet Requirement Checklist
A1: Requirement (from project brief) | B1: Where to find it | C1: Function(s) used | D1: Status
A2: Enter & format data (bold, italic, currency, date) | B2: All data sheets (headers bold, ₹ currency, dd-mmm-yyyy dates; italic notes on Analysis) | C2: Number formats | D2: Done
A3: Absolute & relative references | B3: Analysis rows 28-135 ($A$1:$B$2 style); Sales Data N2:N21 uses $P$1 | C3: $A$1, A1 | D3: Done
A4: Classify grades (nested IF) | B4: Students Grade col G; Analysis section 1 | C4: IF (nested) | D4: Done
A5: Discount by price threshold | B5: Sales Data cols G:I | C5: IF (nested) | D5: Done
A6: Math & Science > 80 | B6: Students Grade col I | C6: IF + AND | D6: Done
A7: Product discount eligibility | B7: Sales Data col J | C7: IF + OR | D7: Done
A8: Students scoring above 50 in Math | B8: Analysis B30 | C8: COUNTIFS | D8: Done
A9: Students scoring above 60 | B9: Analysis B28:B29 | C9: COUNTIFS | D9: Done
A10: Total sales for region & product | B10: Analysis C44 | C10: SUMIFS | D10: Done
A11: Average score above 60 | B11: Analysis B46 | C11: AVERAGEIFS | D11: Done
A12: Student name by ID | B12: Analysis B50 | C12: VLOOKUP | D12: Done
... A25: Top-performing students (grades above 80) | B25: Analysis A135:C142 | C25: FILTER | D25: Done
